rak811/__init__.py
rak811/cli.py
rak811/cli_v3.py
rak811/exception.py
rak811/rak811.py
rak811/rak811_v3.py
rak811/serial.py
rak811-0.8.5.dist-info/LICENSE.txt
rak811-0.8.5.dist-info/METADATA
rak811-0.8.5.dist-info/WHEEL
rak811-0.8.5.dist-info/entry_points.txt
rak811-0.8.5.dist-info/top_level.txt
rak811-0.8.5.dist-info/RECORD
