Metadata-Version: 2.1
Name: rak811
Version: 0.8.5
Summary: Interface for RAK811 LoRa module
Home-page: https://github.com/AmedeeBulle/pyrak811
Author: Philippe Vanhaesendonck
Author-email: philippe.vanhaesendonck@e-bulles.be
License: UNKNOWN
Platform: UNKNOWN
Classifier: Development Status :: 4 - Beta
Classifier: Intended Audience :: Developers
Classifier: Topic :: Software Development :: Libraries
Classifier: License :: OSI Approved :: Apache Software License
Classifier: Programming Language :: Python :: 3
Classifier: Operating System :: POSIX :: Linux
Requires-Python: >=3.5
License-File: LICENSE.txt
Requires-Dist: click (>=7.1)
Requires-Dist: pyserial
Requires-Dist: setuptools
Requires-Dist: RPi.GPIO ; platform_machine == "armv7l" or platform_machine == "armv6l"
Provides-Extra: test
Requires-Dist: flake8 ; extra == 'test'
Requires-Dist: flake8-comprehensions ; extra == 'test'
Requires-Dist: flake8-docstrings ; extra == 'test'
Requires-Dist: flake8-import-order ; extra == 'test'
Requires-Dist: pep8-naming ; extra == 'test'
Requires-Dist: pydocstyle (==6.0.0) ; extra == 'test'
Requires-Dist: pytest ; extra == 'test'
Requires-Dist: mock ; extra == 'test'
Requires-Dist: coverage ; extra == 'test'
Requires-Dist: tox ; extra == 'test'
